{
  "id": "2759683",
  "name": "MyBlog",
  "font_family": "iconfont",
  "css_prefix_text": "icon-",
  "description": "",
  "glyphs": [
    {
      "icon_id": "10070462",
      "name": "搜索--1",
      "font_class": "search",
      "unicode": "e600",
      "unicode_decimal": 58880
    },
    {
      "icon_id": "10457743",
      "name": "csdn logo",
      "font_class": "csdnlogo",
      "unicode": "e619",
      "unicode_decimal": 58905
    },
    {
      "icon_id": "13906375",
      "name": "leetcode",
      "font_class": "leetcode",
      "unicode": "e604",
      "unicode_decimal": 58884
    },
    {
      "icon_id": "16745321",
      "name": "bilibili",
      "font_class": "bilibili",
      "unicode": "e601",
      "unicode_decimal": 58881
    },
    {
      "icon_id": "17278037",
      "name": "信箱",
      "font_class": "xinxiang",
      "unicode": "e640",
      "unicode_decimal": 58944
    },
    {
      "icon_id": "18749258",
      "name": "博客",
      "font_class": "1230",
      "unicode": "e691",
      "unicode_decimal": 59025
    }
  ]
}
